<?xml version="1.0" encoding="utf-8"?>
<versioncheck spoof="1216205754" bspit="1217502896">
  <idn>:com:net:no:jp:de:se:kr:tw:cn:at:dk:ch:li:museum:hu:xn--kgbechtv:xn--hgbk6aj7f53bba:xn--0zwm56d:xn--g6w251d:xn--80akhbyknj4f:xn--11b5bs3a9aj6g:xn--jxalpdlp:xn--9t4b11yi5a:xn--deba0ad:xn--zckzah:xn--hlcj6aya9esc7a:</idn>
  <latestversion lang="af"><%VERSION%></latestversion>
  <latestversion lang="be"><%VERSION%></latestversion>
  <latestversion lang="bg"><%VERSION%></latestversion>
  <latestversion lang="ca"><%VERSION%></latestversion>
  <latestversion lang="cs"><%VERSION%></latestversion>
  <latestversion lang="da"><%VERSION%></latestversion>
  <latestversion lang="de"><%VERSION%></latestversion>
  <latestversion lang="el"><%VERSION%></latestversion>
  <latestversion lang="en"><%VERSION%></latestversion>
  <latestversion lang="en-gb"><%VERSION%></latestversion>
  <latestversion lang="en-us"><%VERSION%></latestversion>
  <latestversion lang="es-es"><%VERSION%></latestversion>
  <latestversion lang="es-la"><%VERSION%></latestversion>
  <latestversion lang="fi"><%VERSION%></latestversion>
  <latestversion lang="fr"><%VERSION%></latestversion>
  <latestversion lang="fr-ca"><%VERSION%></latestversion>
  <latestversion lang="fy"><%VERSION%></latestversion>
  <latestversion lang="hi"><%VERSION%></latestversion>
  <latestversion lang="hr"><%VERSION%></latestversion>
  <latestversion lang="hu"><%VERSION%></latestversion>
  <latestversion lang="id"><%VERSION%></latestversion>
  <latestversion lang="it"><%VERSION%></latestversion>
  <latestversion lang="ja"><%VERSION%></latestversion>
  <latestversion lang="ka"><%VERSION%></latestversion>
  <latestversion lang="ko"><%VERSION%></latestversion>
  <latestversion lang="lt"><%VERSION%></latestversion>
  <latestversion lang="mk"><%VERSION%></latestversion>
  <latestversion lang="nb"><%VERSION%></latestversion>
  <latestversion lang="nl"><%VERSION%></latestversion>
  <latestversion lang="nn"><%VERSION%></latestversion>
  <latestversion lang="pa"><%VERSION%></latestversion>
  <latestversion lang="pl"><%VERSION%></latestversion>
  <latestversion lang="pt"><%VERSION%></latestversion>
  <latestversion lang="pt-br"><%VERSION%></latestversion>
  <latestversion lang="ru"><%VERSION%></latestversion>
  <latestversion lang="sv"><%VERSION%></latestversion>
  <latestversion lang="th"><%VERSION%></latestversion>
  <latestversion lang="tr"><%VERSION%></latestversion>
  <latestversion lang="zh-cn"><%VERSION%></latestversion>
  <latestversion lang="zh-tw"><%VERSION%></latestversion>
</versioncheck>
